Workbook

Sheet Dashboard
A1: PR.2 Sales Analyzer – Executive Dashboard
A2: ="Orders from "&TEXT(MIN(Dataset!$H$2:$H$201),"dd mmm yyyy")&" to "&TEXT(MAX(Dataset!$H$2:$H$201),"dd mmm yyyy")&" | Last refreshed: "&TEXT(NOW(),"dd mmm yyyy hh:mm:ss") -> Orders from 10 Apr 2024 to 07 Apr 2025 | Last refreshed: 14 Oct 2026 11:38:36
A4: TOTAL SALES | C4: TOTAL PROFIT | E4: PROFIT MARGIN | G4: TOTAL ORDERS | I4: AVG DISCOUNT | K4: TOP REGION
A5: =SUM(Dataset!$E$2:$E$201) -> 195217.76 | C5: =SUM(Dataset!$I$2:$I$201) -> 68287.01 | E5: =SUM(Dataset!$I$2:$I$201)/SUM(Dataset!$E$2:$E$201) -> 0.34979917 | G5: =COUNT(Dataset!$E$2:$E$201) -> 200 | I5: =AVERAGE(Dataset!$G$2:$G$201) -> 0.09725 | K5: =INDEX(Pivot_Summary!$A$6:$A$10,MATCH(MAX(Pivot_Summary!$G$6:$G$10),Pivot_Summary!$G$6:$G$10,0)) -> West
A6: ="Avg per order: "&TEXT(AVERAGE(Dataset!$E$2:$E$201),"#,##0") -> Avg per order: 976 | C6: ="Avg per order: "&TEXT(AVERAGE(Dataset!$I$2:$I$201),"#,##0") -> Avg per order: 341 | E6: ="Profit ÷ Sales" -> Profit ÷ Sales | G6: =COUNTA(Customer_Analysis!$A$10:$A$39)&" customers" -> 30 customers | I6: ="Max "&TEXT(MAX(Dataset!$G$2:$G$201),"0%")&" per order" -> Max 20% per order | K6: =TEXT(MAX(Pivot_Summary!$H$6:$H$10),"0.0%")&" of total sales" -> 22.6% of total sales
A8: Key Insights (generated automatically from the data)
A9: ="1. Total sales of "&TEXT(SUM(Dataset!$E$2:$E$201),"#,##0")&" produced profit of "&TEXT(SUM(Dataset!$I$2:$I$201),"#,##0")&" ("&TEXT(SUM(Dataset!$I$2:$I$201)/SUM(Dataset!$E$2:$E$201),"0.0%")&" margin) across "&COUNT(Dataset!$E$2:$E$201)&" orders and "&COUNTA(Customer_Analysis!$A$10:$A$39)&" customers." -> 1. Total sales of 195,218 produced profit of 68,287 (35.0% margin) across 200 orders and 30 customers.
A10: ="2. Best region: "&INDEX(Pivot_Summary!$A$6:$A$10,MATCH(MAX(Pivot_Summary!$G$6:$G$10),Pivot_Summary!$G$6:$G$10,0))&" ("&TEXT(MAX(Pivot_Summary!$H$6:$H$10),"0.0%")&" of sales); weakest region: "&INDEX(Pivot_Summary!$A$6:$A$10,MATCH(MIN(Pivot_Summary!$G$6:$G$10),Pivot_Summary!$G$6:$G$10,0))&" ("&TEXT(MIN(Pivot_Summary!$H$6:$H$10),"0.0%")&")." -> 2. Best region: West (22.6% of sales); weakest region: East (16.6%).
A11: ="3. Best product category: "&INDEX(Pivot_Summary!$B$5:$F$5,MATCH(MAX(Pivot_Summary!$B$11:$F$11),Pivot_Summary!$B$11:$F$11,0))&" ("&TEXT(MAX(Pivot_Summary!$B$12:$F$12),"0.0%")&" of sales); weakest: "&INDEX(Pivot_Summary!$B$5:$F$5,MATCH(MIN(Pivot_Summary!$B$11:$F$11),Pivot_Summary!$B$11:$F$11,0))&" ("&TEXT(MIN(Pivot_Summary!$B$12:$F$12),"0.0%")&")." -> 3. Best product category: Books (24.1% of sales); weakest: Office Supplies (14.7%).
A12: ="4. The top 10 customers contribute "&TEXT(SUM(Customer_Analysis!$L$10:$L$19)/SUM(Dataset!$E$2:$E$201),"0.0%")&" of total sales; "&Customer_Analysis!$B$7&" customers are high-value (sales ≥ "&TEXT(Customer_Analysis!$B$6,"#,##0")&"). Leader: "&Customer_Analysis!$K$10&"." -> 4. The top 10 customers contribute 47.3% of total sales; 8 customers are high-value (sales ≥ 8,236). Leader: CUST015.
A13: ="5. Strongest full month: "&TEXT(INDEX(Monthly_Growth!$A$6:$A$17,MATCH(MAX(Monthly_Growth!$C$6:$C$17),Monthly_Growth!$C$6:$C$17,0)),"mmm yyyy")&" ("&TEXT(MAX(Monthly_Growth!$C$6:$C$17),"#,##0")&"); weakest: "&TEXT(INDEX(Monthly_Growth!$A$6:$A$17,MATCH(MIN(Monthly_Growth!$C$6:$C$17),Monthly_Growth!$C$6:$C$17,0)),"mmm yyyy")&" ("&TEXT(MIN(Monthly_Growth!$C$6:$C$17),"#,##0")&"). Latest month is partial." -> 5. Strongest full month: Sep 2024 (20,534); weakest: Aug 2024 (10,092). Latest month is partial.
A14: ="6. Regression: every extra 1 unit of Sales is linked with "&TEXT(Regression!$B$20,"0.000")&" units of Profit (R² = "&TEXT(Regression!$B$6,"0.00")&", "&IF(Regression!$F$13<0.05,"statistically significant","not significant")&")." -> 6. Regression: every extra 1 unit of Sales is linked with 0.351 units of Profit (R² = 0.60, statistically significant).
A15: ="7. What-if: a "&TEXT(What_If!$B$5*100,"+0.0;-0.0;0.0")&" pp change in discount moves total profit by "&TEXT(What_If!$E$14,"+0.0%;-0.0%;0.0%")&" (assuming "&TEXT(What_If!$B$6,"0.0%")&" volume uplift per pp)." -> 7. What-if: a +5.0 pp change in discount moves total profit by -3.4% (assuming 3.0% volume uplift per pp).
A17: Visual Analysis

Sheet Dataset
A1: Customer_ID | B1: Customer_Name | C1: Region | D1: Product_Category | E1: Sales | F1: Quantity | G1: Discount | H1: Order_Date | I1: Profit | J1: Timestamp | L1: Timestamp column (Task 6): =NOW() – refreshes every time the workbook recalculates.
A2: CUST019 | B2: James Davis | C2: West | D2: Books | E2: 1036.09 | F2: 4 | G2: 0.2 | H2: 45392 | I2: 331.55 | J2: =NOW() -> 46309.485
A3: CUST012 | B3: Robert Anderson | C3: West | D3: Clothing | E3: 1101.28 | F3: 3 | G3: 0.2 | H3: 45393 | I3: 440.51 | J3: =NOW() -> 46309.485
A4: CUST017 | B4: James Taylor | C4: East | D4: Books | E4: 713.34 | F4: 17 | G4: 0 | H4: 45396 | I4: 285.34 | J4: =NOW() -> 46309.485
A5: CUST005 | B5: Robert Anderson | C5: South | D5: Electronics | E5: 760.93 | F5: 4 | G5: 0.15 | H5: 45396 | I5: 161.7 | J5: =NOW() -> 46309.485
A6: CUST030 | B6: James Wilson | C6: North | D6: Books | E6: 847 | F6: 12 | G6: 0.2 | H6: 45397 | I6: 271.04 | J6: =NOW() -> 46309.485
A7: CUST007 | B7: Michael Anderson | C7: North | D7: Furniture | E7: 965.64 | F7: 8 | G7: 0.1 | H7: 45398 | I7: 304.18 | J7: =NOW() -> 46309.485
A8: CUST001 | B8: Linda Wilson | C8: West | D8: Electronics | E8: 1317.53 | F8: 12 | G8: 0.05 | H8: 45398 | I8: 312.91 | J8: =NOW() -> 46309.485
A9: CUST026 | B9: Mary Davis | C9: East | D9: Furniture | E9: 1074.47 | F9: 6 | G9: 0.2 | H9: 45401 | I9: 300.85 | J9: =NOW() -> 46309.485
A10: CUST009 | B10: Linda Jackson | C10: Central | D10: Books | E10: 501.54 | F10: 11 | G10: 0.05 | H10: 45401 | I10: 190.59 | J10: =NOW() -> 46309.485
A11: CUST010 | B11: David Thomas | C11: Central | D11: Clothing | E11: 737.31 | F11: 2 | G11: 0.05 | H11: 45401 | I11: 350.22 | J11: =NOW() -> 46309.485
A12: CUST014 | B12: Emma Davis | C12: West | D12: Office Supplies | E12: 1572.82 | F12: 6 | G12: 0.05 | H12: 45402 | I12: 672.38 | J12: =NOW() -> 46309.485
A13: CUST014 | B13: David Thomas | C13: Central | D13: Books | E13: 1343.13 | F13: 14 | G13: 0.15 | H13: 45404 | I13: 456.66 | J13: =NOW() -> 46309.485
... A201: CUST016 | B201: David Thomas | C201: South | D201: Clothing | E201: 928.32 | F201: 2 | G201: 0.05 | H201: 45754 | I201: 440.95 | J201: =NOW() -> 46309.485

Sheet Customer_Analysis
A1: Customer Analysis
A2: Task 1: Top-10 customers via conditional formatting | Task 7: High-value customers via GROUP-BY (SUMIF) + INDEX / MATCH + filters
A4: High-Value Rule | J4: Key
A5: High-value percentile cut-off | B5: 0.75 | J5: Gold rows = Top 10 customers by Total Sales (Conditional Formatting)
A6: High-value threshold (Total Sales ≥) | B6: =PERCENTILE($C$10:$C$39,B5) -> 8236.4275 | J6: Blue cells with yellow fill = editable inputs
A7: High-value customers (count) | B7: =COUNTIF($H$10:$H$39,"High-Value") -> 8 | J7: Customers are grouped by Customer_ID (see Notes_Checks)
J8: Top 10 Customers – looked up with INDEX / MATCH
A9: Customer_ID | B9: Orders | C9: Total Sales | D9: Total Profit | E9: Avg Order Value | F9: Profit Margin | G9: Sales Rank | H9: Segment | J9: Rank | K9: Customer_ID | L9: Total Sales | M9: Total Profit | N9: Orders | O9: Segment
A10: CUST001 | B10: =COUNTIF(Dataset!$A$2:$A$201,$A10) -> 7 | C10: =SUMIF(Dataset!$A$2:$A$201,$A10,Dataset!$E$2:$E$201) -> 6549.55 | D10: =SUMIF(Dataset!$A$2:$A$201,$A10,Dataset!$I$2:$I$201) -> 1868.77 | E10: =IF(B10=0,0,C10/B10) -> 935.65 | F10: =IF(C10=0,0,D10/C10) -> 0.285328 | G10: =RANK(C10,$C$10:$C$39,0)+COUNTIF($C$10:C10,C10)-1 -> 15 | H10: =IF(C10>=$B$6,"High-Value","Regular") -> Regular | J10: 1 | K10: =INDEX($A$10:$A$39,MATCH($J10,$G$10:$G$39,0)) -> CUST015 | L10: =INDEX($C$10:$C$39,MATCH($J10,$G$10:$G$39,0)) -> 11611.06 | M10: =INDEX($D$10:$D$39,MATCH($J10,$G$10:$G$39,0)) -> 4201.59 | N10: =INDEX($B$10:$B$39,MATCH($J10,$G$10:$G$39,0)) -> 11 | O10: =INDEX($H$10:$H$39,MATCH($J10,$G$10:$G$39,0)) -> High-Value
A11: CUST002 | B11: =COUNTIF(Dataset!$A$2:$A$201,$A11) -> 6 | C11: =SUMIF(Dataset!$A$2:$A$201,$A11,Dataset!$E$2:$E$201) -> 6481.43 | D11: =SUMIF(Dataset!$A$2:$A$201,$A11,Dataset!$I$2:$I$201) -> 2210.74 | E11: =IF(B11=0,0,C11/B11) -> 1080.2383 | F11: =IF(C11=0,0,D11/C11) -> 0.34108831 | G11: =RANK(C11,$C$10:$C$39,0)+COUNTIF($C$10:C11,C11)-1 -> 17 | H11: =IF(C11>=$B$6,"High-Value","Regular") -> Regular | J11: 2 | K11: =INDEX($A$10:$A$39,MATCH($J11,$G$10:$G$39,0)) -> CUST028 | L11: =INDEX($C$10:$C$39,MATCH($J11,$G$10:$G$39,0)) -> 10293.87 | M11: =INDEX($D$10:$D$39,MATCH($J11,$G$10:$G$39,0)) -> 3541.02 | N11: =INDEX($B$10:$B$39,MATCH($J11,$G$10:$G$39,0)) -> 12 | O11: =INDEX($H$10:$H$39,MATCH($J11,$G$10:$G$39,0)) -> High-Value
A12: CUST003 | B12: =COUNTIF(Dataset!$A$2:$A$201,$A12) -> 9 | C12: =SUMIF(Dataset!$A$2:$A$201,$A12,Dataset!$E$2:$E$201) -> 8490.18 | D12: =SUMIF(Dataset!$A$2:$A$201,$A12,Dataset!$I$2:$I$201) -> 2652.75 | E12: =IF(B12=0,0,C12/B12) -> 943.35333 | F12: =IF(C12=0,0,D12/C12) -> 0.31244921 | G12: =RANK(C12,$C$10:$C$39,0)+COUNTIF($C$10:C12,C12)-1 -> 7 | H12: =IF(C12>=$B$6,"High-Value","Regular") -> High-Value | J12: 3 | K12: =INDEX($A$10:$A$39,MATCH($J12,$G$10:$G$39,0)) -> CUST007 | L12: =INDEX($C$10:$C$39,MATCH($J12,$G$10:$G$39,0)) -> 9941.88 | M12: =INDEX($D$10:$D$39,MATCH($J12,$G$10:$G$39,0)) -> 3936.26 | N12: =INDEX($B$10:$B$39,MATCH($J12,$G$10:$G$39,0)) -> 10 | O12: =INDEX($H$10:$H$39,MATCH($J12,$G$10:$G$39,0)) -> High-Value
A13: CUST004 | B13: =COUNTIF(Dataset!$A$2:$A$201,$A13) -> 7 | C13: =SUMIF(Dataset!$A$2:$A$201,$A13,Dataset!$E$2:$E$201) -> 7813.59 | D13: =SUMIF(Dataset!$A$2:$A$201,$A13,Dataset!$I$2:$I$201) -> 3211.82 | E13: =IF(B13=0,0,C13/B13) -> 1116.2271 | F13: =IF(C13=0,0,D13/C13) -> 0.41105561 | G13: =RANK(C13,$C$10:$C$39,0)+COUNTIF($C$10:C13,C13)-1 -> 10 | H13: =IF(C13>=$B$6,"High-Value","Regular") -> Regular | J13: 4 | K13: =INDEX($A$10:$A$39,MATCH($J13,$G$10:$G$39,0)) -> CUST008 | L13: =INDEX($C$10:$C$39,MATCH($J13,$G$10:$G$39,0)) -> 9760.8 | M13: =INDEX($D$10:$D$39,MATCH($J13,$G$10:$G$39,0)) -> 3442.48 | N13: =INDEX($B$10:$B$39,MATCH($J13,$G$10:$G$39,0)) -> 10 | O13: =INDEX($H$10:$H$39,MATCH($J13,$G$10:$G$39,0)) -> High-Value
A14: CUST005 | B14: =COUNTIF(Dataset!$A$2:$A$201,$A14) -> 6 | C14: =SUMIF(Dataset!$A$2:$A$201,$A14,Dataset!$E$2:$E$201) -> 6666.13 | D14: =SUMIF(Dataset!$A$2:$A$201,$A14,Dataset!$I$2:$I$201) -> 1982.39 | E14: =IF(B14=0,0,C14/B14) -> 1111.0217 | F14: =IF(C14=0,0,D14/C14) -> 0.29738244 | G14: =RANK(C14,$C$10:$C$39,0)+COUNTIF($C$10:C14,C14)-1 -> 14 | H14: =IF(C14>=$B$6,"High-Value","Regular") -> Regular | J14: 5 | K14: =INDEX($A$10:$A$39,MATCH($J14,$G$10:$G$39,0)) -> CUST026 | L14: =INDEX($C$10:$C$39,MATCH($J14,$G$10:$G$39,0)) -> 9371.81 | M14: =INDEX($D$10:$D$39,MATCH($J14,$G$10:$G$39,0)) -> 2922.02 | N14: =INDEX($B$10:$B$39,MATCH($J14,$G$10:$G$39,0)) -> 9 | O14: =INDEX($H$10:$H$39,MATCH($J14,$G$10:$G$39,0)) -> High-Value
A15: CUST006 | B15: =COUNTIF(Dataset!$A$2:$A$201,$A15) -> 2 | C15: =SUMIF(Dataset!$A$2:$A$201,$A15,Dataset!$E$2:$E$201) -> 2699.75 | D15: =SUMIF(Dataset!$A$2:$A$201,$A15,Dataset!$I$2:$I$201) -> 837.06 | E15: =IF(B15=0,0,C15/B15) -> 1349.875 | F15: =IF(C15=0,0,D15/C15) -> 0.31005093 | G15: =RANK(C15,$C$10:$C$39,0)+COUNTIF($C$10:C15,C15)-1 -> 30 | H15: =IF(C15>=$B$6,"High-Value","Regular") -> Regular | J15: 6 | K15: =INDEX($A$10:$A$39,MATCH($J15,$G$10:$G$39,0)) -> CUST021 | L15: =INDEX($C$10:$C$39,MATCH($J15,$G$10:$G$39,0)) -> 8740.18 | M15: =INDEX($D$10:$D$39,MATCH($J15,$G$10:$G$39,0)) -> 2848.62 | N15: =INDEX($B$10:$B$39,MATCH($J15,$G$10:$G$39,0)) -> 8 | O15: =INDEX($H$10:$H$39,MATCH($J15,$G$10:$G$39,0)) -> High-Value
A16: CUST007 | B16: =COUNTIF(Dataset!$A$2:$A$201,$A16) -> 10 | C16: =SUMIF(Dataset!$A$2:$A$201,$A16,Dataset!$E$2:$E$201) -> 9941.88 | D16: =SUMIF(Dataset!$A$2:$A$201,$A16,Dataset!$I$2:$I$201) -> 3936.26 | E16: =IF(B16=0,0,C16/B16) -> 994.188 | F16: =IF(C16=0,0,D16/C16) -> 0.39592713 | G16: =RANK(C16,$C$10:$C$39,0)+COUNTIF($C$10:C16,C16)-1 -> 3 | H16: =IF(C16>=$B$6,"High-Value","Regular") -> High-Value | J16: 7 | K16: =INDEX($A$10:$A$39,MATCH($J16,$G$10:$G$39,0)) -> CUST003 | L16: =INDEX($C$10:$C$39,MATCH($J16,$G$10:$G$39,0)) -> 8490.18 | M16: =INDEX($D$10:$D$39,MATCH($J16,$G$10:$G$39,0)) -> 2652.75 | N16: =INDEX($B$10:$B$39,MATCH($J16,$G$10:$G$39,0)) -> 9 | O16: =INDEX($H$10:$H$39,MATCH($J16,$G$10:$G$39,0)) -> High-Value
A17: CUST008 | B17: =COUNTIF(Dataset!$A$2:$A$201,$A17) -> 10 | C17: =SUMIF(Dataset!$A$2:$A$201,$A17,Dataset!$E$2:$E$201) -> 9760.8 | D17: =SUMIF(Dataset!$A$2:$A$201,$A17,Dataset!$I$2:$I$201) -> 3442.48 | E17: =IF(B17=0,0,C17/B17) -> 976.08 | F17: =IF(C17=0,0,D17/C17) -> 0.35268421 | G17: =RANK(C17,$C$10:$C$39,0)+COUNTIF($C$10:C17,C17)-1 -> 4 | H17: =IF(C17>=$B$6,"High-Value","Regular") -> High-Value | J17: 8 | K17: =INDEX($A$10:$A$39,MATCH($J17,$G$10:$G$39,0)) -> CUST012 | L17: =INDEX($C$10:$C$39,MATCH($J17,$G$10:$G$39,0)) -> 8339 | M17: =INDEX($D$10:$D$39,MATCH($J17,$G$10:$G$39,0)) -> 2988.71 | N17: =INDEX($B$10:$B$39,MATCH($J17,$G$10:$G$39,0)) -> 9 | O17: =INDEX($H$10:$H$39,MATCH($J17,$G$10:$G$39,0)) -> High-Value
A18: CUST009 | B18: =COUNTIF(Dataset!$A$2:$A$201,$A18) -> 7 | C18: =SUMIF(Dataset!$A$2:$A$201,$A18,Dataset!$E$2:$E$201) -> 6505.2 | D18: =SUMIF(Dataset!$A$2:$A$201,$A18,Dataset!$I$2:$I$201) -> 2052.54 | E18: =IF(B18=0,0,C18/B18) -> 929.31429 | F18: =IF(C18=0,0,D18/C18) -> 0.31552297 | G18: =RANK(C18,$C$10:$C$39,0)+COUNTIF($C$10:C18,C18)-1 -> 16 | H18: =IF(C18>=$B$6,"High-Value","Regular") -> Regular | J18: 9 | K18: =INDEX($A$10:$A$39,MATCH($J18,$G$10:$G$39,0)) -> CUST030 | L18: =INDEX($C$10:$C$39,MATCH($J18,$G$10:$G$39,0)) -> 7928.71 | M18: =INDEX($D$10:$D$39,MATCH($J18,$G$10:$G$39,0)) -> 2965.48 | N18: =INDEX($B$10:$B$39,MATCH($J18,$G$10:$G$39,0)) -> 9 | O18: =INDEX($H$10:$H$39,MATCH($J18,$G$10:$G$39,0)) -> Regular
A19: CUST010 | B19: =COUNTIF(Dataset!$A$2:$A$201,$A19) -> 5 | C19: =SUMIF(Dataset!$A$2:$A$201,$A19,Dataset!$E$2:$E$201) -> 4259.22 | D19: =SUMIF(Dataset!$A$2:$A$201,$A19,Dataset!$I$2:$I$201) -> 1529.32 | E19: =IF(B19=0,0,C19/B19) -> 851.844 | F19: =IF(C19=0,0,D19/C19) -> 0.35906105 | G19: =RANK(C19,$C$10:$C$39,0)+COUNTIF($C$10:C19,C19)-1 -> 24 | H19: =IF(C19>=$B$6,"High-Value","Regular") -> Regular | J19: 10 | K19: =INDEX($A$10:$A$39,MATCH($J19,$G$10:$G$39,0)) -> CUST004 | L19: =INDEX($C$10:$C$39,MATCH($J19,$G$10:$G$39,0)) -> 7813.59 | M19: =INDEX($D$10:$D$39,MATCH($J19,$G$10:$G$39,0)) -> 3211.82 | N19: =INDEX($B$10:$B$39,MATCH($J19,$G$10:$G$39,0)) -> 7 | O19: =INDEX($H$10:$H$39,MATCH($J19,$G$10:$G$39,0)) -> Regular
A20: CUST011 | B20: =COUNTIF(Dataset!$A$2:$A$201,$A20) -> 4 | C20: =SUMIF(Dataset!$A$2:$A$201,$A20,Dataset!$E$2:$E$201) -> 3762.29 | D20: =SUMIF(Dataset!$A$2:$A$201,$A20,Dataset!$I$2:$I$201) -> 1545.04 | E20: =IF(B20=0,0,C20/B20) -> 940.5725 | F20: =IF(C20=0,0,D20/C20) -> 0.41066478 | G20: =RANK(C20,$C$10:$C$39,0)+COUNTIF($C$10:C20,C20)-1 -> 27 | H20: =IF(C20>=$B$6,"High-Value","Regular") -> Regular
A21: CUST012 | B21: =COUNTIF(Dataset!$A$2:$A$201,$A21) -> 9 | C21: =SUMIF(Dataset!$A$2:$A$201,$A21,Dataset!$E$2:$E$201) -> 8339 | D21: =SUMIF(Dataset!$A$2:$A$201,$A21,Dataset!$I$2:$I$201) -> 2988.71 | E21: =IF(B21=0,0,C21/B21) -> 926.55556 | F21: =IF(C21=0,0,D21/C21) -> 0.35840149 | G21: =RANK(C21,$C$10:$C$39,0)+COUNTIF($C$10:C21,C21)-1 -> 8 | H21: =IF(C21>=$B$6,"High-Value","Regular") -> High-Value
A22: CUST013 | B22: =COUNTIF(Dataset!$A$2:$A$201,$A22) -> 4 | C22: =SUMIF(Dataset!$A$2:$A$201,$A22,Dataset!$E$2:$E$201) -> 4162.44 | D22: =SUMIF(Dataset!$A$2:$A$201,$A22,Dataset!$I$2:$I$201) -> 1605.11 | E22: =IF(B22=0,0,C22/B22) -> 1040.61 | F22: =IF(C22=0,0,D22/C22) -> 0.38561757 | G22: =RANK(C22,$C$10:$C$39,0)+COUNTIF($C$10:C22,C22)-1 -> 25 | H22: =IF(C22>=$B$6,"High-Value","Regular") -> Regular | J22: Customer Lookup (type or pick a Customer_ID)
A23: CUST014 | B23: =COUNTIF(Dataset!$A$2:$A$201,$A23) -> 6 | C23: =SUMIF(Dataset!$A$2:$A$201,$A23,Dataset!$E$2:$E$201) -> 6729.89 | D23: =SUMIF(Dataset!$A$2:$A$201,$A23,Dataset!$I$2:$I$201) -> 2507.18 | E23: =IF(B23=0,0,C23/B23) -> 1121.6483 | F23: =IF(C23=0,0,D23/C23) -> 0.37254398 | G23: =RANK(C23,$C$10:$C$39,0)+COUNTIF($C$10:C23,C23)-1 -> 12 | H23: =IF(C23>=$B$6,"High-Value","Regular") -> Regular | J23: Customer_ID | L23: CUST012
A24: CUST015 | B24: =COUNTIF(Dataset!$A$2:$A$201,$A24) -> 11 | C24: =SUMIF(Dataset!$A$2:$A$201,$A24,Dataset!$E$2:$E$201) -> 11611.06 | D24: =SUMIF(Dataset!$A$2:$A$201,$A24,Dataset!$I$2:$I$201) -> 4201.59 | E24: =IF(B24=0,0,C24/B24) -> 1055.5509 | F24: =IF(C24=0,0,D24/C24) -> 0.36186102 | G24: =RANK(C24,$C$10:$C$39,0)+COUNTIF($C$10:C24,C24)-1 -> 1 | H24: =IF(C24>=$B$6,"High-Value","Regular") -> High-Value | J24: Orders | L24: =IFERROR(INDEX($B$10:$B$39,MATCH($L$23,$A$10:$A$39,0)),"Not found") -> 9
A25: CUST016 | B25: =COUNTIF(Dataset!$A$2:$A$201,$A25) -> 4 | C25: =SUMIF(Dataset!$A$2:$A$201,$A25,Dataset!$E$2:$E$201) -> 3369.17 | D25: =SUMIF(Dataset!$A$2:$A$201,$A25,Dataset!$I$2:$I$201) -> 1497.25 | E25: =IF(B25=0,0,C25/B25) -> 842.2925 | F25: =IF(C25=0,0,D25/C25) -> 0.44439728 | G25: =RANK(C25,$C$10:$C$39,0)+COUNTIF($C$10:C25,C25)-1 -> 29 | H25: =IF(C25>=$B$6,"High-Value","Regular") -> Regular | J25: Total Sales | L25: =IFERROR(INDEX($C$10:$C$39,MATCH($L$23,$A$10:$A$39,0)),"Not found") -> 8339
A26: CUST017 | B26: =COUNTIF(Dataset!$A$2:$A$201,$A26) -> 4 | C26: =SUMIF(Dataset!$A$2:$A$201,$A26,Dataset!$E$2:$E$201) -> 3419.2 | D26: =SUMIF(Dataset!$A$2:$A$201,$A26,Dataset!$I$2:$I$201) -> 1257.21 | E26: =IF(B26=0,0,C26/B26) -> 854.8 | F26: =IF(C26=0,0,D26/C26) -> 0.36769127 | G26: =RANK(C26,$C$10:$C$39,0)+COUNTIF($C$10:C26,C26)-1 -> 28 | H26: =IF(C26>=$B$6,"High-Value","Regular") -> Regular | J26: Total Profit | L26: =IFERROR(INDEX($D$10:$D$39,MATCH($L$23,$A$10:$A$39,0)),"Not found") -> 2988.71
A27: CUST018 | B27: =COUNTIF(Dataset!$A$2:$A$201,$A27) -> 5 | C27: =SUMIF(Dataset!$A$2:$A$201,$A27,Dataset!$E$2:$E$201) -> 4951.89 | D27: =SUMIF(Dataset!$A$2:$A$201,$A27,Dataset!$I$2:$I$201) -> 1821.64 | E27: =IF(B27=0,0,C27/B27) -> 990.378 | F27: =IF(C27=0,0,D27/C27) -> 0.36786762 | G27: =RANK(C27,$C$10:$C$39,0)+COUNTIF($C$10:C27,C27)-1 -> 20 | H27: =IF(C27>=$B$6,"High-Value","Regular") -> Regular | J27: Sales Rank | L27: =IFERROR(INDEX($G$10:$G$39,MATCH($L$23,$A$10:$A$39,0)),"Not found") -> 8
A28: CUST019 | B28: =COUNTIF(Dataset!$A$2:$A$201,$A28) -> 5 | C28: =SUMIF(Dataset!$A$2:$A$201,$A28,Dataset!$E$2:$E$201) -> 4640.11 | D28: =SUMIF(Dataset!$A$2:$A$201,$A28,Dataset!$I$2:$I$201) -> 1721.12 | E28: =IF(B28=0,0,C28/B28) -> 928.022 | F28: =IF(C28=0,0,D28/C28) -> 0.37092224 | G28: =RANK(C28,$C$10:$C$39,0)+COUNTIF($C$10:C28,C28)-1 -> 21 | H28: =IF(C28>=$B$6,"High-Value","Regular") -> Regular | J28: Segment | L28: =IFERROR(INDEX($H$10:$H$39,MATCH($L$23,$A$10:$A$39,0)),"Not found") -> High-Value
A29: CUST020 | B29: =COUNTIF(Dataset!$A$2:$A$201,$A29) -> 4 | C29: =SUMIF(Dataset!$A$2:$A$201,$A29,Dataset!$E$2:$E$201) -> 4413.71 | D29: =SUMIF(Dataset!$A$2:$A$201,$A29,Dataset!$I$2:$I$201) -> 1664.79 | E29: =IF(B29=0,0,C29/B29) -> 1103.4275 | F29: =IF(C29=0,0,D29/C29) -> 0.37718609 | G29: =RANK(C29,$C$10:$C$39,0)+COUNTIF($C$10:C29,C29)-1 -> 23 | H29: =IF(C29>=$B$6,"High-Value","Regular") -> Regular
A30: CUST021 | B30: =COUNTIF(Dataset!$A$2:$A$201,$A30) -> 8 | C30: =SUMIF(Dataset!$A$2:$A$201,$A30,Dataset!$E$2:$E$201) -> 8740.18 | D30: =SUMIF(Dataset!$A$2:$A$201,$A30,Dataset!$I$2:$I$201) -> 2848.62 | E30: =IF(B30=0,0,C30/B30) -> 1092.5225 | F30: =IF(C30=0,0,D30/C30) -> 0.32592235 | G30: =RANK(C30,$C$10:$C$39,0)+COUNTIF($C$10:C30,C30)-1 -> 6 | H30: =IF(C30>=$B$6,"High-Value","Regular") -> High-Value
A31: CUST022 | B31: =COUNTIF(Dataset!$A$2:$A$201,$A31) -> 5 | C31: =SUMIF(Dataset!$A$2:$A$201,$A31,Dataset!$E$2:$E$201) -> 4418.28 | D31: =SUMIF(Dataset!$A$2:$A$201,$A31,Dataset!$I$2:$I$201) -> 1605.23 | E31: =IF(B31=0,0,C31/B31) -> 883.656 | F31: =IF(C31=0,0,D31/C31) -> 0.36331559 | G31: =RANK(C31,$C$10:$C$39,0)+COUNTIF($C$10:C31,C31)-1 -> 22 | H31: =IF(C31>=$B$6,"High-Value","Regular") -> Regular
A32: CUST023 | B32: =COUNTIF(Dataset!$A$2:$A$201,$A32) -> 7 | C32: =SUMIF(Dataset!$A$2:$A$201,$A32,Dataset!$E$2:$E$201) -> 5913.68 | D32: =SUMIF(Dataset!$A$2:$A$201,$A32,Dataset!$I$2:$I$201) -> 2198.62 | E32: =IF(B32=0,0,C32/B32) -> 844.81143 | F32: =IF(C32=0,0,D32/C32) -> 0.37178542 | G32: =RANK(C32,$C$10:$C$39,0)+COUNTIF($C$10:C32,C32)-1 -> 18 | H32: =IF(C32>=$B$6,"High-Value","Regular") -> Regular
A33: CUST024 | B33: =COUNTIF(Dataset!$A$2:$A$201,$A33) -> 7 | C33: =SUMIF(Dataset!$A$2:$A$201,$A33,Dataset!$E$2:$E$201) -> 7583.13 | D33: =SUMIF(Dataset!$A$2:$A$201,$A33,Dataset!$I$2:$I$201) -> 2492.1 | E33: =IF(B33=0,0,C33/B33) -> 1083.3043 | F33: =IF(C33=0,0,D33/C33) -> 0.32863738 | G33: =RANK(C33,$C$10:$C$39,0)+COUNTIF($C$10:C33,C33)-1 -> 11 | H33: =IF(C33>=$B$6,"High-Value","Regular") -> Regular
A34: CUST025 | B34: =COUNTIF(Dataset!$A$2:$A$201,$A34) -> 6 | C34: =SUMIF(Dataset!$A$2:$A$201,$A34,Dataset!$E$2:$E$201) -> 6716.52 | D34: =SUMIF(Dataset!$A$2:$A$201,$A34,Dataset!$I$2:$I$201) -> 2327.84 | E34: =IF(B34=0,0,C34/B34) -> 1119.42 | F34: =IF(C34=0,0,D34/C34) -> 0.34658424 | G34: =RANK(C34,$C$10:$C$39,0)+COUNTIF($C$10:C34,C34)-1 -> 13 | H34: =IF(C34>=$B$6,"High-Value","Regular") -> Regular
A35: CUST026 | B35: =COUNTIF(Dataset!$A$2:$A$201,$A35) -> 9 | C35: =SUMIF(Dataset!$A$2:$A$201,$A35,Dataset!$E$2:$E$201) -> 9371.81 | D35: =SUMIF(Dataset!$A$2:$A$201,$A35,Dataset!$I$2:$I$201) -> 2922.02 | E35: =IF(B35=0,0,C35/B35) -> 1041.3122 | F35: =IF(C35=0,0,D35/C35) -> 0.31178822 | G35: =RANK(C35,$C$10:$C$39,0)+COUNTIF($C$10:C35,C35)-1 -> 5 | H35: =IF(C35>=$B$6,"High-Value","Regular") -> High-Value
A36: CUST027 | B36: =COUNTIF(Dataset!$A$2:$A$201,$A36) -> 5 | C36: =SUMIF(Dataset!$A$2:$A$201,$A36,Dataset!$E$2:$E$201) -> 3906.04 | D36: =SUMIF(Dataset!$A$2:$A$201,$A36,Dataset!$I$2:$I$201) -> 1240.65 | E36: =IF(B36=0,0,C36/B36) -> 781.208 | F36: =IF(C36=0,0,D36/C36) -> 0.31762348 | G36: =RANK(C36,$C$10:$C$39,0)+COUNTIF($C$10:C36,C36)-1 -> 26 | H36: =IF(C36>=$B$6,"High-Value","Regular") -> Regular
A37: CUST028 | B37: =COUNTIF(Dataset!$A$2:$A$201,$A37) -> 12 | C37: =SUMIF(Dataset!$A$2:$A$201,$A37,Dataset!$E$2:$E$201) -> 10293.87 | D37: =SUMIF(Dataset!$A$2:$A$201,$A37,Dataset!$I$2:$I$201) -> 3541.02 | E37: =IF(B37=0,0,C37/B37) -> 857.8225 | F37: =IF(C37=0,0,D37/C37) -> 0.34399308 | G37: =RANK(C37,$C$10:$C$39,0)+COUNTIF($C$10:C37,C37)-1 -> 2 | H37: =IF(C37>=$B$6,"High-Value","Regular") -> High-Value
A38: CUST029 | B38: =COUNTIF(Dataset!$A$2:$A$201,$A38) -> 7 | C38: =SUMIF(Dataset!$A$2:$A$201,$A38,Dataset!$E$2:$E$201) -> 5779.05 | D38: =SUMIF(Dataset!$A$2:$A$201,$A38,Dataset!$I$2:$I$201) -> 1611.66 | E38: =IF(B38=0,0,C38/B38) -> 825.57857 | F38: =IF(C38=0,0,D38/C38) -> 0.27887975 | G38: =RANK(C38,$C$10:$C$39,0)+COUNTIF($C$10:C38,C38)-1 -> 19 | H38: =IF(C38>=$B$6,"High-Value","Regular") -> Regular
A39: CUST030 | B39: =COUNTIF(Dataset!$A$2:$A$201,$A39) -> 9 | C39: =SUMIF(Dataset!$A$2:$A$201,$A39,Dataset!$E$2:$E$201) -> 7928.71 | D39: =SUMIF(Dataset!$A$2:$A$201,$A39,Dataset!$I$2:$I$201) -> 2965.48 | E39: =IF(B39=0,0,C39/B39) -> 880.96778 | F39: =IF(C39=0,0,D39/C39) -> 0.37401797 | G39: =RANK(C39,$C$10:$C$39,0)+COUNTIF($C$10:C39,C39)-1 -> 9 | H39: =IF(C39>=$B$6,"High-Value","Regular") -> Regular
A40: Total | B40: =SUM(B10:B39) -> 200 | C40: =SUM(C10:C39) -> 195217.76 | D40: =SUM(D10:D39) -> 68287.01 | E40: =IF(B40=0,0,C40/B40) -> 976.0888 | F40: =IF(C40=0,0,D40/C40) -> 0.34979917

Sheet What_If
A1: What-If Analysis – Discount vs Total Profit
A2: Task 2: change the yellow inputs and watch profit react; the sensitivity table shows the whole range at once
A4: Scenario Inputs (editable)
A5: Change in discount (percentage points, e.g. 0.05 = +5 pp) | B5: 0.05
A6: Volume uplift per +1 pp of discount (assumption) | B6: 0.03
A7: Volume factor applied to quantity sold | B7: =MAX(0,1+B6*B5*100) -> 1.15
A9: Baseline vs Scenario
A10: Metric | B10: Baseline | C10: Scenario | D10: Change | E10: % Change
A11: Average discount | B11: =AVERAGE(Dataset!$G$2:$G$201) -> 0.09725 | C11: =SUMPRODUCT((Dataset!$G$2:$G$201+$B$5)*((Dataset!$G$2:$G$201+$B$5)>0))/COUNT(Dataset!$G$2:$G$201) -> 0.14725 | D11: =C11-B11 -> 0.05
A12: Net sales | B12: =SUM(Dataset!$E$2:$E$201) -> 195217.76 | C12: =SUMPRODUCT(Dataset!$E$2:$E$201/(1-Dataset!$G$2:$G$201)*(1-(Dataset!$G$2:$G$201+$B$5)*((Dataset!$G$2:$G$201+$B$5)>0)))*$B$7 -> 211963.86 | D12: =C12-B12 -> 16746.1 | E12: =IF(B12=0,0,D12/B12) -> 0.085781644
A13: Total cost (Sales − Profit) | B13: =SUM(Dataset!$E$2:$E$201)-SUM(Dataset!$I$2:$I$201) -> 126930.75 | C13: =B13*$B$7 -> 145970.36 | D13: =C13-B13 -> 19039.612 | E13: =IF(B13=0,0,D13/B13) -> 0.15
A14: Total profit | B14: =SUM(Dataset!$I$2:$I$201) -> 68287.01 | C14: =C12-C13 -> 65993.498 | D14: =C14-B14 -> -2293.5122 | E14: =IF(B14=0,0,D14/B14) -> -0.033586361
A15: Profit margin | B15: =B14/B12 -> 0.34979917 | C15: =IF(C12=0,0,C14/C12) -> 0.31134316 | D15: =C15-B15 -> -0.038456009
A18: Sensitivity Table – total profit for a range of discount changes
A19: Discount change (pp) | B19: Average discount | C19: Net sales | D19: Total profit | E19: Profit change vs baseline | F19: % change | G19: Profit margin
A20: -0.1 | B20: =SUMPRODUCT((Dataset!$G$2:$G$201+$A20)*((Dataset!$G$2:$G$201+$A20)>0))/COUNT(Dataset!$G$2:$G$201) -> 0.02925 | C20: =SUMPRODUCT(Dataset!$E$2:$E$201/(1-Dataset!$G$2:$G$201)*(1-(Dataset!$G$2:$G$201+$A20)*((Dataset!$G$2:$G$201+$A20)>0)))*MAX(0,1+$B$6*$A20*100) -> 147542.51 | D20: =C20-($B$12-$B$14)*MAX(0,1+$B$6*$A20*100) -> 58690.986 | E20: =D20-$B$14 -> -9596.0244 | F20: =IF($B$14=0,0,E20/$B$14) -> -0.14052489 | G20: =IF(C20=0,0,D20/C20) -> 0.39779034
A21: -0.075 | B21: =SUMPRODUCT((Dataset!$G$2:$G$201+$A21)*((Dataset!$G$2:$G$201+$A21)>0))/COUNT(Dataset!$G$2:$G$201) -> 0.043625 | C21: =SUMPRODUCT(Dataset!$E$2:$E$201/(1-Dataset!$G$2:$G$201)*(1-(Dataset!$G$2:$G$201+$A21)*((Dataset!$G$2:$G$201+$A21)>0)))*MAX(0,1+$B$6*$A21*100) -> 160745.46 | D21: =C21-($B$12-$B$14)*MAX(0,1+$B$6*$A21*100) -> 62374.13 | E21: =D21-$B$14 -> -5912.8804 | F21: =IF($B$14=0,0,E21/$B$14) -> -0.086588656 | G21: =IF(C21=0,0,D21/C21) -> 0.38803043
A22: -0.05 | B22: =SUMPRODUCT((Dataset!$G$2:$G$201+$A22)*((Dataset!$G$2:$G$201+$A22)>0))/COUNT(Dataset!$G$2:$G$201) -> 0.058 | C22: =SUMPRODUCT(Dataset!$E$2:$E$201/(1-Dataset!$G$2:$G$201)*(1-(Dataset!$G$2:$G$201+$A22)*((Dataset!$G$2:$G$201+$A22)>0)))*MAX(0,1+$B$6*$A22*100) -> 173444.18 | D22: =C22-($B$12-$B$14)*MAX(0,1+$B$6*$A22*100) -> 65553.046 | E22: =D22-$B$14 -> -2733.9639 | F22: =IF($B$14=0,0,E22/$B$14) -> -0.040036369 | G22: =IF(C22=0,0,D22/C22) -> 0.37794894
A23: -0.025 | B23: =SUMPRODUCT((Dataset!$G$2:$G$201+$A23)*((Dataset!$G$2:$G$201+$A23)>0))/COUNT(Dataset!$G$2:$G$201) -> 0.077625 | C23: =SUMPRODUCT(Dataset!$E$2:$E$201/(1-Dataset!$G$2:$G$201)*(1-(Dataset!$G$2:$G$201+$A23)*((Dataset!$G$2:$G$201+$A23)>0)))*MAX(0,1+$B$6*$A23*100) -> 184662.26 | D23: =C23-($B$12-$B$14)*MAX(0,1+$B$6*$A23*100) -> 67251.311 | E23: =D23-$B$14 -> -1035.6987 | F23: =IF($B$14=0,0,E23/$B$14) -> -0.015166848 | G23: =IF(C23=0,0,D23/C23) -> 0.36418548
A24: 0 | B24: =SUMPRODUCT((Dataset!$G$2:$G$201+$A24)*((Dataset!$G$2:$G$201+$A24)>0))/COUNT(Dataset!$G$2:$G$201) -> 0.09725 | C24: =SUMPRODUCT(Dataset!$E$2:$E$201/(1-Dataset!$G$2:$G$201)*(1-(Dataset!$G$2:$G$201+$A24)*((Dataset!$G$2:$G$201+$A24)>0)))*MAX(0,1+$B$6*$A24*100) -> 195217.76 | D24: =C24-($B$12-$B$14)*MAX(0,1+$B$6*$A24*100) -> 68287.01 | E24: =D24-$B$14 -> 0 | F24: =IF($B$14=0,0,E24/$B$14) -> 0 | G24: =IF(C24=0,0,D24/C24) -> 0.34979917
A25: 0.025 | B25: =SUMPRODUCT((Dataset!$G$2:$G$201+$A25)*((Dataset!$G$2:$G$201+$A25)>0))/COUNT(Dataset!$G$2:$G$201) -> 0.12225 | C25: =SUMPRODUCT(Dataset!$E$2:$E$201/(1-Dataset!$G$2:$G$201)*(1-(Dataset!$G$2:$G$201+$A25)*((Dataset!$G$2:$G$201+$A25)>0)))*MAX(0,1+$B$6*$A25*100) -> 203999.61 | D25: =C25-($B$12-$B$14)*MAX(0,1+$B$6*$A25*100) -> 67549.055 | E25: =D25-$B$14 -> -737.95509 | F25: =IF($B$14=0,0,E25/$B$14) -> -0.010806669 | G25: =IF(C25=0,0,D25/C25) -> 0.33112345
A26: 0.05 | B26: =SUMPRODUCT((Dataset!$G$2:$G$201+$A26)*((Dataset!$G$2:$G$201+$A26)>0))/COUNT(Dataset!$G$2:$G$201) -> 0.14725 | C26: =SUMPRODUCT(Dataset!$E$2:$E$201/(1-Dataset!$G$2:$G$201)*(1-(Dataset!$G$2:$G$201+$A26)*((Dataset!$G$2:$G$201+$A26)>0)))*MAX(0,1+$B$6*$A26*100) -> 211963.86 | D26: =C26-($B$12-$B$14)*MAX(0,1+$B$6*$A26*100) -> 65993.498 | E26: =D26-$B$14 -> -2293.5122 | F26: =IF($B$14=0,0,E26/$B$14) -> -0.033586361 | G26: =IF(C26=0,0,D26/C26) -> 0.31134316
A27: 0.075 | B27: =SUMPRODUCT((Dataset!$G$2:$G$201+$A27)*((Dataset!$G$2:$G$201+$A27)>0))/COUNT(Dataset!$G$2:$G$201) -> 0.17225 | C27: =SUMPRODUCT(Dataset!$E$2:$E$201/(1-Dataset!$G$2:$G$201)*(1-(Dataset!$G$2:$G$201+$A27)*((Dataset!$G$2:$G$201+$A27)>0)))*MAX(0,1+$B$6*$A27*100) -> 219110.51 | D27: =C27-($B$12-$B$14)*MAX(0,1+$B$6*$A27*100) -> 63620.339 | E27: =D27-$B$14 -> -4666.6712 | F27: =IF($B$14=0,0,E27/$B$14) -> -0.068339076 | G27: =IF(C27=0,0,D27/C27) -> 0.29035732
A28: 0.1 | B28: =SUMPRODUCT((Dataset!$G$2:$G$201+$A28)*((Dataset!$G$2:$G$201+$A28)>0))/COUNT(Dataset!$G$2:$G$201) -> 0.19725 | C28: =SUMPRODUCT(Dataset!$E$2:$E$201/(1-Dataset!$G$2:$G$201)*(1-(Dataset!$G$2:$G$201+$A28)*((Dataset!$G$2:$G$201+$A28)>0)))*MAX(0,1+$B$6*$A28*100) -> 225439.55 | D28: =C28-($B$12-$B$14)*MAX(0,1+$B$6*$A28*100) -> 60429.578 | E28: =D28-$B$14 -> -7857.4322 | F28: =IF($B$14=0,0,E28/$B$14) -> -0.11506482 | G28: =IF(C28=0,0,D28/C28) -> 0.26805224

Sheet Regression
A1: Linear Regression – Profit vs Sales
A2: Task 3: output laid out like Data Analysis ToolPak ▸ Regression (Y = Profit, X = Sales), calculated with live formulas
A4: Regression Statistics
A5: Multiple R | B5: =ABS(CORREL(Dataset!$I$2:$I$201,Dataset!$E$2:$E$201)) -> 0.77340306
A6: R Square | B6: =RSQ(Dataset!$I$2:$I$201,Dataset!$E$2:$E$201) -> 0.5981523
A7: Adjusted R Square | B7: =1-(1-B6)*(B9-1)/(B9-2) -> 0.59612277
A8: Standard Error | B8: =STEYX(Dataset!$I$2:$I$201,Dataset!$E$2:$E$201) -> 86.281231
A9: Observations | B9: =COUNT(Dataset!$E$2:$E$201) -> 200
A11: ANOVA
B12: df | C12: SS | D12: MS | E12: F | F12: Significance F
A13: Regression | B13: 1 | C13: =B6*DEVSQ(Dataset!$I$2:$I$201) -> 2194058.2 | D13: =C13/B13 -> 2194058.2 | E13: =D13/D14 -> 294.72398 | F13: =FDIST(E13,B13,B14) -> 4.6269368e-41
A14: Residual | B14: =B9-2 -> 198 | C14: =(1-B6)*DEVSQ(Dataset!$I$2:$I$201) -> 1474001.2 | D14: =C14/B14 -> 7444.4507
A15: Total | B15: =B9-1 -> 199 | C15: =DEVSQ(Dataset!$I$2:$I$201) -> 3668059.4
A17: Coefficients
B18: Coefficients | C18: Standard Error | D18: t Stat | E18: P-value | F18: Lower 95% | G18: Upper 95%
A19: Intercept | B19: =INTERCEPT(Dataset!$I$2:$I$201,Dataset!$E$2:$E$201) -> -1.0315505 | C19: =B8*SQRT(1/B9+AVERAGE(Dataset!$E$2:$E$201)^2/DEVSQ(Dataset!$E$2:$E$201)) -> 20.860617 | D19: =B19/C19 -> -0.049449663 | E19: =TDIST(ABS(D19),$B$14,2) -> 0.9606108 | F19: =B19-TINV(0.05,$B$14)*C19 -> -42.169052 | G19: =B19+TINV(0.05,$B$14)*C19 -> 40.105951
A20: Sales (X variable) | B20: =SLOPE(Dataset!$I$2:$I$201,Dataset!$E$2:$E$201) -> 0.35085599 | C20: =B8/SQRT(DEVSQ(Dataset!$E$2:$E$201)) -> 0.020437189 | D20: =B20/C20 -> 17.167527 | E20: =TDIST(ABS(D20),$B$14,2) -> 4.6269368e-41 | F20: =B20-TINV(0.05,$B$14)*C20 -> 0.3105535 | G20: =B20+TINV(0.05,$B$14)*C20 -> 0.39115848
A22: Interpretation (updates automatically)
A23: ="Equation: Profit = "&TEXT(B20,"0.0000")&" × Sales "&TEXT(B19,"+ 0.00;- 0.00") -> Equation: Profit = 0.3509 × Sales - 1.03
A24: ="Sales explains "&TEXT(B6,"0.0%")&" of the variation in Profit (R² = "&TEXT(B6,"0.000")&"); each extra 1 unit of Sales adds about "&TEXT(B20,"0.000")&" units of Profit." -> Sales explains 59.8% of the variation in Profit (R² = 0.598); each extra 1 unit of Sales adds about 0.351 units of Profit.
A25: =IF(F13<0.05,"The relationship is statistically significant (Significance F = "&TEXT(F13,"0.0000")&" < 0.05).","The relationship is NOT statistically significant at the 5% level (Significance F = "&TEXT(F13,"0.0000")&").") -> The relationship is statistically significant (Significance F = 0.0000 < 0.05).
A27: Predict Profit for a given Sales value
A28: Sales (enter value) | B28: 1000
A29: Predicted Profit | B29: =B19+B20*B28 -> 349.82444

Sheet Descriptive_Stats
A1: Descriptive Statistics & Histogram
A2: Task 4: replicates Data Analysis ToolPak ▸ Descriptive Statistics and Histogram using live formulas
A5: Statistic | B5: Sales | C5: Quantity | D5: Discount | E5: Profit
A6: Mean | B6: =AVERAGE(Dataset!$E$2:$E$201) -> 976.0888 | C6: =AVERAGE(Dataset!$F$2:$F$201) -> 9.995 | D6: =AVERAGE(Dataset!$G$2:$G$201) -> 0.09725 | E6: =AVERAGE(Dataset!$I$2:$I$201) -> 341.43505
A7: Standard Error | B7: =STDEV(Dataset!$E$2:$E$201)/SQRT(COUNT(Dataset!$E$2:$E$201)) -> 21.16185 | C7: =STDEV(Dataset!$F$2:$F$201)/SQRT(COUNT(Dataset!$F$2:$F$201)) -> 0.39927683 | D7: =STDEV(Dataset!$G$2:$G$201)/SQRT(COUNT(Dataset!$G$2:$G$201)) -> 0.0051142414 | E7: =STDEV(Dataset!$I$2:$I$201)/SQRT(COUNT(Dataset!$I$2:$I$201)) -> 9.6001196
A8: Median | B8: =MEDIAN(Dataset!$E$2:$E$201) -> 976.72 | C8: =MEDIAN(Dataset!$F$2:$F$201) -> 10 | D8: =MEDIAN(Dataset!$G$2:$G$201) -> 0.1 | E8: =MEDIAN(Dataset!$I$2:$I$201) -> 332.255
A9: Mode | B9: =IFERROR(MODE(Dataset!$E$2:$E$201),"No mode") -> No mode | C9: =IFERROR(MODE(Dataset!$F$2:$F$201),"No mode") -> 8 | D9: =IFERROR(MODE(Dataset!$G$2:$G$201),"No mode") -> 0.2 | E9: =IFERROR(MODE(Dataset!$I$2:$I$201),"No mode") -> No mode
A10: Standard Deviation | B10: =STDEV(Dataset!$E$2:$E$201) -> 299.27376 | C10: =STDEV(Dataset!$F$2:$F$201) -> 5.646627 | D10: =STDEV(Dataset!$G$2:$G$201) -> 0.072326295 | E10: =STDEV(Dataset!$I$2:$I$201) -> 135.76619
A11: Sample Variance | B11: =VAR(Dataset!$E$2:$E$201) -> 89564.783 | C11: =VAR(Dataset!$F$2:$F$201) -> 31.884397 | D11: =VAR(Dataset!$G$2:$G$201) -> 0.005231093 | E11: =VAR(Dataset!$I$2:$I$201) -> 18432.459
A12: Kurtosis | B12: =KURT(Dataset!$E$2:$E$201) -> -0.088595232 | C12: =KURT(Dataset!$F$2:$F$201) -> -1.2091054 | D12: =KURT(Dataset!$G$2:$G$201) -> -1.3257012 | E12: =KURT(Dataset!$I$2:$I$201) -> 0.26450644
A13: Skewness | B13: =SKEW(Dataset!$E$2:$E$201) -> 0.14685797 | C13: =SKEW(Dataset!$F$2:$F$201) -> 0.060845864 | D13: =SKEW(Dataset!$G$2:$G$201) -> 0.096827386 | E13: =SKEW(Dataset!$I$2:$I$201) -> 0.57339636
A14: Range | B14: =MAX(Dataset!$E$2:$E$201)-MIN(Dataset!$E$2:$E$201) -> 1665.15 | C14: =MAX(Dataset!$F$2:$F$201)-MIN(Dataset!$F$2:$F$201) -> 18 | D14: =MAX(Dataset!$G$2:$G$201)-MIN(Dataset!$G$2:$G$201) -> 0.2 | E14: =MAX(Dataset!$I$2:$I$201)-MIN(Dataset!$I$2:$I$201) -> 704.83
A15: Minimum | B15: =MIN(Dataset!$E$2:$E$201) -> 258.51 | C15: =MIN(Dataset!$F$2:$F$201) -> 1 | D15: =MIN(Dataset!$G$2:$G$201) -> 0 | E15: =MIN(Dataset!$I$2:$I$201) -> 64.63
A16: Maximum | B16: =MAX(Dataset!$E$2:$E$201) -> 1923.66 | C16: =MAX(Dataset!$F$2:$F$201) -> 19 | D16: =MAX(Dataset!$G$2:$G$201) -> 0.2 | E16: =MAX(Dataset!$I$2:$I$201) -> 769.46
A17: Sum | B17: =SUM(Dataset!$E$2:$E$201) -> 195217.76 | C17: =SUM(Dataset!$F$2:$F$201) -> 1999 | D17: =SUM(Dataset!$G$2:$G$201) -> 19.45 | E17: =SUM(Dataset!$I$2:$I$201) -> 68287.01
A18: Count | B18: =COUNT(Dataset!$E$2:$E$201) -> 200 | C18: =COUNT(Dataset!$F$2:$F$201) -> 200 | D18: =COUNT(Dataset!$G$2:$G$201) -> 200 | E18: =COUNT(Dataset!$I$2:$I$201) -> 200
A19: Confidence Level (95.0%) | B19: =TINV(0.05,COUNT(Dataset!$E$2:$E$201)-1)*STDEV(Dataset!$E$2:$E$201)/SQRT(COUNT(Dataset!$E$2:$E$201)) -> 41.730249 | C19: =TINV(0.05,COUNT(Dataset!$F$2:$F$201)-1)*STDEV(Dataset!$F$2:$F$201)/SQRT(COUNT(Dataset!$F$2:$F$201)) -> 0.78735655 | D19: =TINV(0.05,COUNT(Dataset!$G$2:$G$201)-1)*STDEV(Dataset!$G$2:$G$201)/SQRT(COUNT(Dataset!$G$2:$G$201)) -> 0.010085062 | E19: =TINV(0.05,COUNT(Dataset!$I$2:$I$201)-1)*STDEV(Dataset!$I$2:$I$201)/SQRT(COUNT(Dataset!$I$2:$I$201)) -> 18.931019
A22: Histogram – Sales distribution (bins are editable)
A23: Bin Upper Limit | B23: Bin Range | C23: Frequency | D23: % of Orders | E23: Cumulative %
A24: 500 | B24: =TEXT(0,"#,##0")&" – "&TEXT(A24,"#,##0") -> 0 – 500 | C24: =COUNTIFS(Dataset!$E$2:$E$201,">"&0,Dataset!$E$2:$E$201,"<="&A24) -> 11 | D24: =C24/$C$31 -> 0.055 | E24: =SUM($C$24:C24)/$C$31 -> 0.055
A25: 750 | B25: =TEXT(A24,"#,##0")&" – "&TEXT(A25,"#,##0") -> 500 – 750 | C25: =COUNTIFS(Dataset!$E$2:$E$201,">"&A24,Dataset!$E$2:$E$201,"<="&A25) -> 37 | D25: =C25/$C$31 -> 0.185 | E25: =SUM($C$24:C25)/$C$31 -> 0.24
A26: 1000 | B26: =TEXT(A25,"#,##0")&" – "&TEXT(A26,"#,##0") -> 750 – 1,000 | C26: =COUNTIFS(Dataset!$E$2:$E$201,">"&A25,Dataset!$E$2:$E$201,"<="&A26) -> 58 | D26: =C26/$C$31 -> 0.29 | E26: =SUM($C$24:C26)/$C$31 -> 0.53
A27: 1250 | B27: =TEXT(A26,"#,##0")&" – "&TEXT(A27,"#,##0") -> 1,000 – 1,250 | C27: =COUNTIFS(Dataset!$E$2:$E$201,">"&A26,Dataset!$E$2:$E$201,"<="&A27) -> 60 | D27: =C27/$C$31 -> 0.3 | E27: =SUM($C$24:C27)/$C$31 -> 0.83
A28: 1500 | B28: =TEXT(A27,"#,##0")&" – "&TEXT(A28,"#,##0") -> 1,250 – 1,500 | C28: =COUNTIFS(Dataset!$E$2:$E$201,">"&A27,Dataset!$E$2:$E$201,"<="&A28) -> 25 | D28: =C28/$C$31 -> 0.125 | E28: =SUM($C$24:C28)/$C$31 -> 0.955
A29: 1750 | B29: =TEXT(A28,"#,##0")&" – "&TEXT(A29,"#,##0") -> 1,500 – 1,750 | C29: =COUNTIFS(Dataset!$E$2:$E$201,">"&A28,Dataset!$E$2:$E$201,"<="&A29) -> 8 | D29: =C29/$C$31 -> 0.04 | E29: =SUM($C$24:C29)/$C$31 -> 0.995
A30: 2000 | B30: =TEXT(A29,"#,##0")&" – "&TEXT(A30,"#,##0") -> 1,750 – 2,000 | C30: =COUNTIFS(Dataset!$E$2:$E$201,">"&A29,Dataset!$E$2:$E$201,"<="&A30) -> 1 | D30: =C30/$C$31 -> 0.005 | E30: =SUM($C$24:C30)/$C$31 -> 1
A31: Total | C31: =SUM(C24:C30) -> 200 | D31: =SUM(D24:D30) -> 1
A33: ="Sales: mean "&TEXT(B6,"#,##0")&" vs median "&TEXT(B8,"#,##0")&" – the distribution is "&IF(ABS(B13)<0.5,"roughly symmetric",IF(B13>0,"right-skewed","left-skewed"))&" (skewness "&TEXT(B13,"0.00")&")." -> Sales: mean 976 vs median 977 – the distribution is roughly symmetric (skewness 0.15).
A34: ="Profit: mean "&TEXT(E6,"#,##0")&", standard deviation "&TEXT(E10,"#,##0")&" – typical order profit lies roughly between "&TEXT(E6-E10,"#,##0")&" and "&TEXT(E6+E10,"#,##0")&"." -> Profit: mean 341, standard deviation 136 – typical order profit lies roughly between 206 and 477.

Sheet Monthly_Growth
A1: Monthly Sales Growth
A2: Task 5: ▲/▼ arrows via custom number formats | Task 6: timestamp (see Dataset column J)
A5: Month | B5: Orders | C5: Sales | D5: Profit | E5: Sales Change | F5: Sales Growth % (MoM) | G5: Profit Growth % (MoM) | H5: Avg Order Value
A6: =DATE(YEAR(MIN(Dataset!$H$2:$H$201)),MONTH(MIN(Dataset!$H$2:$H$201)),1) -> 45383 | B6: =COUNTIFS(Dataset!$H$2:$H$201,">="&$A6,Dataset!$H$2:$H$201,"<"&EDATE($A6,1)) -> 19 | C6: =SUMIFS(Dataset!$E$2:$E$201,Dataset!$H$2:$H$201,">="&$A6,Dataset!$H$2:$H$201,"<"&EDATE($A6,1)) -> 19029.96 | D6: =SUMIFS(Dataset!$I$2:$I$201,Dataset!$H$2:$H$201,">="&$A6,Dataset!$H$2:$H$201,"<"&EDATE($A6,1)) -> 6244.01 | E6: n/a | F6: n/a | G6: n/a | H6: =IF(B6=0,0,C6/B6) -> 1001.5768
A7: =EDATE(A6,1) -> 45413 | B7: =COUNTIFS(Dataset!$H$2:$H$201,">="&$A7,Dataset!$H$2:$H$201,"<"&EDATE($A7,1)) -> 21 | C7: =SUMIFS(Dataset!$E$2:$E$201,Dataset!$H$2:$H$201,">="&$A7,Dataset!$H$2:$H$201,"<"&EDATE($A7,1)) -> 18507.34 | D7: =SUMIFS(Dataset!$I$2:$I$201,Dataset!$H$2:$H$201,">="&$A7,Dataset!$H$2:$H$201,"<"&EDATE($A7,1)) -> 6121.35 | E7: =C7-C6 -> -522.62 | F7: =IF(C6=0,0,(C7-C6)/C6) -> -0.027463011 | G7: =IF(D6=0,0,(D7-D6)/D6) -> -0.019644427 | H7: =IF(B7=0,0,C7/B7) -> 881.3019
A8: =EDATE(A7,1) -> 45444 | B8: =COUNTIFS(Dataset!$H$2:$H$201,">="&$A8,Dataset!$H$2:$H$201,"<"&EDATE($A8,1)) -> 20 | C8: =SUMIFS(Dataset!$E$2:$E$201,Dataset!$H$2:$H$201,">="&$A8,Dataset!$H$2:$H$201,"<"&EDATE($A8,1)) -> 20187.51 | D8: =SUMIFS(Dataset!$I$2:$I$201,Dataset!$H$2:$H$201,">="&$A8,Dataset!$H$2:$H$201,"<"&EDATE($A8,1)) -> 6918 | E8: =C8-C7 -> 1680.17 | F8: =IF(C7=0,0,(C8-C7)/C7) -> 0.090783981 | G8: =IF(D7=0,0,(D8-D7)/D7) -> 0.13014286 | H8: =IF(B8=0,0,C8/B8) -> 1009.3755
A9: =EDATE(A8,1) -> 45474 | B9: =COUNTIFS(Dataset!$H$2:$H$201,">="&$A9,Dataset!$H$2:$H$201,"<"&EDATE($A9,1)) -> 12 | C9: =SUMIFS(Dataset!$E$2:$E$201,Dataset!$H$2:$H$201,">="&$A9,Dataset!$H$2:$H$201,"<"&EDATE($A9,1)) -> 11609.04 | D9: =SUMIFS(Dataset!$I$2:$I$201,Dataset!$H$2:$H$201,">="&$A9,Dataset!$H$2:$H$201,"<"&EDATE($A9,1)) -> 3743.85 | E9: =C9-C8 -> -8578.47 | F9: =IF(C8=0,0,(C9-C8)/C8) -> -0.42493948 | G9: =IF(D8=0,0,(D9-D8)/D8) -> -0.4588248 | H9: =IF(B9=0,0,C9/B9) -> 967.42
A10: =EDATE(A9,1) -> 45505 | B10: =COUNTIFS(Dataset!$H$2:$H$201,">="&$A10,Dataset!$H$2:$H$201,"<"&EDATE($A10,1)) -> 10 | C10: =SUMIFS(Dataset!$E$2:$E$201,Dataset!$H$2:$H$201,">="&$A10,Dataset!$H$2:$H$201,"<"&EDATE($A10,1)) -> 10091.7 | D10: =SUMIFS(Dataset!$I$2:$I$201,Dataset!$H$2:$H$201,">="&$A10,Dataset!$H$2:$H$201,"<"&EDATE($A10,1)) -> 3302.84 | E10: =C10-C9 -> -1517.34 | F10: =IF(C9=0,0,(C10-C9)/C9) -> -0.13070331 | G10: =IF(D9=0,0,(D10-D9)/D9) -> -0.11779585 | H10: =IF(B10=0,0,C10/B10) -> 1009.17
A11: =EDATE(A10,1) -> 45536 | B11: =COUNTIFS(Dataset!$H$2:$H$201,">="&$A11,Dataset!$H$2:$H$201,"<"&EDATE($A11,1)) -> 20 | C11: =SUMIFS(Dataset!$E$2:$E$201,Dataset!$H$2:$H$201,">="&$A11,Dataset!$H$2:$H$201,"<"&EDATE($A11,1)) -> 20533.5 | D11: =SUMIFS(Dataset!$I$2:$I$201,Dataset!$H$2:$H$201,">="&$A11,Dataset!$H$2:$H$201,"<"&EDATE($A11,1)) -> 7457.52 | E11: =C11-C10 -> 10441.8 | F11: =IF(C10=0,0,(C11-C10)/C10) -> 1.0346919 | G11: =IF(D10=0,0,(D11-D10)/D10) -> 1.2579114 | H11: =IF(B11=0,0,C11/B11) -> 1026.675
A12: =EDATE(A11,1) -> 45566 | B12: =COUNTIFS(Dataset!$H$2:$H$201,">="&$A12,Dataset!$H$2:$H$201,"<"&EDATE($A12,1)) -> 14 | C12: =SUMIFS(Dataset!$E$2:$E$201,Dataset!$H$2:$H$201,">="&$A12,Dataset!$H$2:$H$201,"<"&EDATE($A12,1)) -> 14215.24 | D12: =SUMIFS(Dataset!$I$2:$I$201,Dataset!$H$2:$H$201,">="&$A12,Dataset!$H$2:$H$201,"<"&EDATE($A12,1)) -> 4861.7 | E12: =C12-C11 -> -6318.26 | F12: =IF(C11=0,0,(C12-C11)/C11) -> -0.30770497 | G12: =IF(D11=0,0,(D12-D11)/D11) -> -0.34808086 | H12: =IF(B12=0,0,C12/B12) -> 1015.3743
A13: =EDATE(A12,1) -> 45597 | B13: =COUNTIFS(Dataset!$H$2:$H$201,">="&$A13,Dataset!$H$2:$H$201,"<"&EDATE($A13,1)) -> 20 | C13: =SUMIFS(Dataset!$E$2:$E$201,Dataset!$H$2:$H$201,">="&$A13,Dataset!$H$2:$H$201,"<"&EDATE($A13,1)) -> 20135.03 | D13: =SUMIFS(Dataset!$I$2:$I$201,Dataset!$H$2:$H$201,">="&$A13,Dataset!$H$2:$H$201,"<"&EDATE($A13,1)) -> 6814.88 | E13: =C13-C12 -> 5919.79 | F13: =IF(C12=0,0,(C13-C12)/C12) -> 0.41643968 | G13: =IF(D12=0,0,(D13-D12)/D12) -> 0.40174836 | H13: =IF(B13=0,0,C13/B13) -> 1006.7515
A14: =EDATE(A13,1) -> 45627 | B14: =COUNTIFS(Dataset!$H$2:$H$201,">="&$A14,Dataset!$H$2:$H$201,"<"&EDATE($A14,1)) -> 11 | C14: =SUMIFS(Dataset!$E$2:$E$201,Dataset!$H$2:$H$201,">="&$A14,Dataset!$H$2:$H$201,"<"&EDATE($A14,1)) -> 11120.04 | D14: =SUMIFS(Dataset!$I$2:$I$201,Dataset!$H$2:$H$201,">="&$A14,Dataset!$H$2:$H$201,"<"&EDATE($A14,1)) -> 3549.99 | E14: =C14-C13 -> -9014.99 | F14: =IF(C13=0,0,(C14-C13)/C13) -> -0.44772667 | G14: =IF(D13=0,0,(D14-D13)/D13) -> -0.47908254 | H14: =IF(B14=0,0,C14/B14) -> 1010.9127
A15: =EDATE(A14,1) -> 45658 | B15: =COUNTIFS(Dataset!$H$2:$H$201,">="&$A15,Dataset!$H$2:$H$201,"<"&EDATE($A15,1)) -> 16 | C15: =SUMIFS(Dataset!$E$2:$E$201,Dataset!$H$2:$H$201,">="&$A15,Dataset!$H$2:$H$201,"<"&EDATE($A15,1)) -> 14914.65 | D15: =SUMIFS(Dataset!$I$2:$I$201,Dataset!$H$2:$H$201,">="&$A15,Dataset!$H$2:$H$201,"<"&EDATE($A15,1)) -> 5763.4 | E15: =C15-C14 -> 3794.61 | F15: =IF(C14=0,0,(C15-C14)/C14) -> 0.34124068 | G15: =IF(D14=0,0,(D15-D14)/D14) -> 0.62349753 | H15: =IF(B15=0,0,C15/B15) -> 932.16563
A16: =EDATE(A15,1) -> 45689 | B16: =COUNTIFS(Dataset!$H$2:$H$201,">="&$A16,Dataset!$H$2:$H$201,"<"&EDATE($A16,1)) -> 14 | C16: =SUMIFS(Dataset!$E$2:$E$201,Dataset!$H$2:$H$201,">="&$A16,Dataset!$H$2:$H$201,"<"&EDATE($A16,1)) -> 14006.36 | D16: =SUMIFS(Dataset!$I$2:$I$201,Dataset!$H$2:$H$201,">="&$A16,Dataset!$H$2:$H$201,"<"&EDATE($A16,1)) -> 5039.23 | E16: =C16-C15 -> -908.29 | F16: =IF(C15=0,0,(C16-C15)/C15) -> -0.060899183 | G16: =IF(D15=0,0,(D16-D15)/D15) -> -0.12564979 | H16: =IF(B16=0,0,C16/B16) -> 1000.4543
A17: =EDATE(A16,1) -> 45717 | B17: =COUNTIFS(Dataset!$H$2:$H$201,">="&$A17,Dataset!$H$2:$H$201,"<"&EDATE($A17,1)) -> 19 | C17: =SUMIFS(Dataset!$E$2:$E$201,Dataset!$H$2:$H$201,">="&$A17,Dataset!$H$2:$H$201,"<"&EDATE($A17,1)) -> 17655.22 | D17: =SUMIFS(Dataset!$I$2:$I$201,Dataset!$H$2:$H$201,">="&$A17,Dataset!$H$2:$H$201,"<"&EDATE($A17,1)) -> 7071.39 | E17: =C17-C16 -> 3648.86 | F17: =IF(C16=0,0,(C17-C16)/C16) -> 0.26051451 | G17: =IF(D16=0,0,(D17-D16)/D16) -> 0.40326796 | H17: =IF(B17=0,0,C17/B17) -> 929.22211
A18: =EDATE(A17,1) -> 45748 | B18: =COUNTIFS(Dataset!$H$2:$H$201,">="&$A18,Dataset!$H$2:$H$201,"<"&EDATE($A18,1)) -> 4 | C18: =SUMIFS(Dataset!$E$2:$E$201,Dataset!$H$2:$H$201,">="&$A18,Dataset!$H$2:$H$201,"<"&EDATE($A18,1)) -> 3212.17 | D18: =SUMIFS(Dataset!$I$2:$I$201,Dataset!$H$2:$H$201,">="&$A18,Dataset!$H$2:$H$201,"<"&EDATE($A18,1)) -> 1398.85 | E18: =C18-C17 -> -14443.05 | F18: =IF(C17=0,0,(C18-C17)/C17) -> -0.81806117 | G18: =IF(D17=0,0,(D18-D17)/D17) -> -0.80218175 | H18: =IF(B18=0,0,C18/B18) -> 803.0425
A19: Total | B19: =SUM(B6:B18) -> 200 | C19: =SUM(C6:C18) -> 195217.76 | D19: =SUM(D6:D18) -> 68287.01 | H19: =IF(B19=0,0,C19/B19) -> 976.0888
A21: ="Note: data runs from "&TEXT(MIN(Dataset!$H$2:$H$201),"dd-mmm-yyyy")&" to "&TEXT(MAX(Dataset!$H$2:$H$201),"dd-mmm-yyyy")&", so the first and last months are partial and their growth rates should be read with care." -> Note: data runs from 10-Apr-2024 to 07-Apr-2025, so the first and last months are partial and their growth rates should be read with care.

Sheet Pivot_Summary
A1: Pivot Summary – Sales by Region and Product
A2: Task 8: pivot-style cross-tab built with SUMIFS so it refreshes automatically with the Dataset sheet
A4: Total Sales by Region × Product Category
A5: Region | B5: Books | C5: Clothing | D5: Electronics | E5: Furniture | F5: Office Supplies | G5: Grand Total | H5: Share % | I5: Rank
A6: Central | B6: =SUMIFS(Dataset!$E$2:$E$201,Dataset!$C$2:$C$201,$A6,Dataset!$D$2:$D$201,B$5) -> 11297.15 | C6: =SUMIFS(Dataset!$E$2:$E$201,Dataset!$C$2:$C$201,$A6,Dataset!$D$2:$D$201,C$5) -> 12200.26 | D6: =SUMIFS(Dataset!$E$2:$E$201,Dataset!$C$2:$C$201,$A6,Dataset!$D$2:$D$201,D$5) -> 6621.24 | E6: =SUMIFS(Dataset!$E$2:$E$201,Dataset!$C$2:$C$201,$A6,Dataset!$D$2:$D$201,E$5) -> 4876.96 | F6: =SUMIFS(Dataset!$E$2:$E$201,Dataset!$C$2:$C$201,$A6,Dataset!$D$2:$D$201,F$5) -> 8472.72 | G6: =SUM(B6:F6) -> 43468.33 | H6: =G6/$G$11 -> 0.22266586 | I6: =RANK(G6,$G$6:$G$10,0) -> 2
A7: East | B7: =SUMIFS(Dataset!$E$2:$E$201,Dataset!$C$2:$C$201,$A7,Dataset!$D$2:$D$201,B$5) -> 11389.09 | C7: =SUMIFS(Dataset!$E$2:$E$201,Dataset!$C$2:$C$201,$A7,Dataset!$D$2:$D$201,C$5) -> 2401.45 | D7: =SUMIFS(Dataset!$E$2:$E$201,Dataset!$C$2:$C$201,$A7,Dataset!$D$2:$D$201,D$5) -> 2869.54 | E7: =SUMIFS(Dataset!$E$2:$E$201,Dataset!$C$2:$C$201,$A7,Dataset!$D$2:$D$201,E$5) -> 7592.34 | F7: =SUMIFS(Dataset!$E$2:$E$201,Dataset!$C$2:$C$201,$A7,Dataset!$D$2:$D$201,F$5) -> 8189.22 | G7: =SUM(B7:F7) -> 32441.64 | H7: =G7/$G$11 -> 0.16618181 | I7: =RANK(G7,$G$6:$G$10,0) -> 5
A8: North | B8: =SUMIFS(Dataset!$E$2:$E$201,Dataset!$C$2:$C$201,$A8,Dataset!$D$2:$D$201,B$5) -> 8037.01 | C8: =SUMIFS(Dataset!$E$2:$E$201,Dataset!$C$2:$C$201,$A8,Dataset!$D$2:$D$201,C$5) -> 8422.82 | D8: =SUMIFS(Dataset!$E$2:$E$201,Dataset!$C$2:$C$201,$A8,Dataset!$D$2:$D$201,D$5) -> 8191.71 | E8: =SUMIFS(Dataset!$E$2:$E$201,Dataset!$C$2:$C$201,$A8,Dataset!$D$2:$D$201,E$5) -> 6978.08 | F8: =SUMIFS(Dataset!$E$2:$E$201,Dataset!$C$2:$C$201,$A8,Dataset!$D$2:$D$201,F$5) -> 3345.8 | G8: =SUM(B8:F8) -> 34975.42 | H8: =G8/$G$11 -> 0.17916106 | I8: =RANK(G8,$G$6:$G$10,0) -> 4
A9: South | B9: =SUMIFS(Dataset!$E$2:$E$201,Dataset!$C$2:$C$201,$A9,Dataset!$D$2:$D$201,B$5) -> 9588.04 | C9: =SUMIFS(Dataset!$E$2:$E$201,Dataset!$C$2:$C$201,$A9,Dataset!$D$2:$D$201,C$5) -> 8393.63 | D9: =SUMIFS(Dataset!$E$2:$E$201,Dataset!$C$2:$C$201,$A9,Dataset!$D$2:$D$201,D$5) -> 11989.07 | E9: =SUMIFS(Dataset!$E$2:$E$201,Dataset!$C$2:$C$201,$A9,Dataset!$D$2:$D$201,E$5) -> 7982.73 | F9: =SUMIFS(Dataset!$E$2:$E$201,Dataset!$C$2:$C$201,$A9,Dataset!$D$2:$D$201,F$5) -> 2295.32 | G9: =SUM(B9:F9) -> 40248.79 | H9: =G9/$G$11 -> 0.20617381 | I9: =RANK(G9,$G$6:$G$10,0) -> 3
A10: West | B10: =SUMIFS(Dataset!$E$2:$E$201,Dataset!$C$2:$C$201,$A10,Dataset!$D$2:$D$201,B$5) -> 6691.17 | C10: =SUMIFS(Dataset!$E$2:$E$201,Dataset!$C$2:$C$201,$A10,Dataset!$D$2:$D$201,C$5) -> 10509.43 | D10: =SUMIFS(Dataset!$E$2:$E$201,Dataset!$C$2:$C$201,$A10,Dataset!$D$2:$D$201,D$5) -> 11372.44 | E10: =SUMIFS(Dataset!$E$2:$E$201,Dataset!$C$2:$C$201,$A10,Dataset!$D$2:$D$201,E$5) -> 9182.78 | F10: =SUMIFS(Dataset!$E$2:$E$201,Dataset!$C$2:$C$201,$A10,Dataset!$D$2:$D$201,F$5) -> 6327.76 | G10: =SUM(B10:F10) -> 44083.58 | H10: =G10/$G$11 -> 0.22581747 | I10: =RANK(G10,$G$6:$G$10,0) -> 1
A11: Grand Total | B11: =SUM(B6:B10) -> 47002.46 | C11: =SUM(C6:C10) -> 41927.59 | D11: =SUM(D6:D10) -> 41044 | E11: =SUM(E6:E10) -> 36612.89 | F11: =SUM(F6:F10) -> 28630.82 | G11: =SUM(G6:G10) -> 195217.76 | H11: =SUM(H6:H10) -> 1
A12: Share % | B12: =B11/$G$11 -> 0.24076938 | C12: =C11/$G$11 -> 0.21477344 | D12: =D11/$G$11 -> 0.21024726 | E12: =E11/$G$11 -> 0.18754897 | F12: =F11/$G$11 -> 0.14666094 | G12: =SUM(B12:F12) -> 1
A14: Total Profit by Region × Product Category
A15: Region | B15: Books | C15: Clothing | D15: Electronics | E15: Furniture | F15: Office Supplies | G15: Grand Total
A16: Central | B16: =SUMIFS(Dataset!$I$2:$I$201,Dataset!$C$2:$C$201,$A16,Dataset!$D$2:$D$201,B$15) -> 4201.27 | C16: =SUMIFS(Dataset!$I$2:$I$201,Dataset!$C$2:$C$201,$A16,Dataset!$D$2:$D$201,C$15) -> 5395.6 | D16: =SUMIFS(Dataset!$I$2:$I$201,Dataset!$C$2:$C$201,$A16,Dataset!$D$2:$D$201,D$15) -> 1515.04 | E16: =SUMIFS(Dataset!$I$2:$I$201,Dataset!$C$2:$C$201,$A16,Dataset!$D$2:$D$201,E$15) -> 1566.46 | F16: =SUMIFS(Dataset!$I$2:$I$201,Dataset!$C$2:$C$201,$A16,Dataset!$D$2:$D$201,F$15) -> 3390.03 | G16: =SUM(B16:F16) -> 16068.4
A17: East | B17: =SUMIFS(Dataset!$I$2:$I$201,Dataset!$C$2:$C$201,$A17,Dataset!$D$2:$D$201,B$15) -> 4212.63 | C17: =SUMIFS(Dataset!$I$2:$I$201,Dataset!$C$2:$C$201,$A17,Dataset!$D$2:$D$201,C$15) -> 1025.15 | D17: =SUMIFS(Dataset!$I$2:$I$201,Dataset!$C$2:$C$201,$A17,Dataset!$D$2:$D$201,D$15) -> 662.68 | E17: =SUMIFS(Dataset!$I$2:$I$201,Dataset!$C$2:$C$201,$A17,Dataset!$D$2:$D$201,E$15) -> 2428.08 | F17: =SUMIFS(Dataset!$I$2:$I$201,Dataset!$C$2:$C$201,$A17,Dataset!$D$2:$D$201,F$15) -> 3310.05 | G17: =SUM(B17:F17) -> 11638.59
A18: North | B18: =SUMIFS(Dataset!$I$2:$I$201,Dataset!$C$2:$C$201,$A18,Dataset!$D$2:$D$201,B$15) -> 2778.44 | C18: =SUMIFS(Dataset!$I$2:$I$201,Dataset!$C$2:$C$201,$A18,Dataset!$D$2:$D$201,C$15) -> 3691.09 | D18: =SUMIFS(Dataset!$I$2:$I$201,Dataset!$C$2:$C$201,$A18,Dataset!$D$2:$D$201,D$15) -> 1783.05 | E18: =SUMIFS(Dataset!$I$2:$I$201,Dataset!$C$2:$C$201,$A18,Dataset!$D$2:$D$201,E$15) -> 2217.72 | F18: =SUMIFS(Dataset!$I$2:$I$201,Dataset!$C$2:$C$201,$A18,Dataset!$D$2:$D$201,F$15) -> 1431.98 | G18: =SUM(B18:F18) -> 11902.28
A19: South | B19: =SUMIFS(Dataset!$I$2:$I$201,Dataset!$C$2:$C$201,$A19,Dataset!$D$2:$D$201,B$15) -> 3416.81 | C19: =SUMIFS(Dataset!$I$2:$I$201,Dataset!$C$2:$C$201,$A19,Dataset!$D$2:$D$201,C$15) -> 3944.21 | D19: =SUMIFS(Dataset!$I$2:$I$201,Dataset!$C$2:$C$201,$A19,Dataset!$D$2:$D$201,D$15) -> 2783.44 | E19: =SUMIFS(Dataset!$I$2:$I$201,Dataset!$C$2:$C$201,$A19,Dataset!$D$2:$D$201,E$15) -> 2540.36 | F19: =SUMIFS(Dataset!$I$2:$I$201,Dataset!$C$2:$C$201,$A19,Dataset!$D$2:$D$201,F$15) -> 1007.09 | G19: =SUM(B19:F19) -> 13691.91
A20: West | B20: =SUMIFS(Dataset!$I$2:$I$201,Dataset!$C$2:$C$201,$A20,Dataset!$D$2:$D$201,B$15) -> 2292.48 | C20: =SUMIFS(Dataset!$I$2:$I$201,Dataset!$C$2:$C$201,$A20,Dataset!$D$2:$D$201,C$15) -> 4728.44 | D20: =SUMIFS(Dataset!$I$2:$I$201,Dataset!$C$2:$C$201,$A20,Dataset!$D$2:$D$201,D$15) -> 2437.94 | E20: =SUMIFS(Dataset!$I$2:$I$201,Dataset!$C$2:$C$201,$A20,Dataset!$D$2:$D$201,E$15) -> 2826.52 | F20: =SUMIFS(Dataset!$I$2:$I$201,Dataset!$C$2:$C$201,$A20,Dataset!$D$2:$D$201,F$15) -> 2700.45 | G20: =SUM(B20:F20) -> 14985.83
A21: Grand Total | B21: =SUM(B16:B20) -> 16901.63 | C21: =SUM(C16:C20) -> 18784.49 | D21: =SUM(D16:D20) -> 9182.15 | E21: =SUM(E16:E20) -> 11579.14 | F21: =SUM(F16:F20) -> 11839.6 | G21: =SUM(G16:G20) -> 68287.01
A24: Profit Margin by Region × Product Category (Profit ÷ Sales)
A25: Region | B25: Books | C25: Clothing | D25: Electronics | E25: Furniture | F25: Office Supplies | G25: Overall
A26: Central | B26: =IF(B6=0,0,B16/B6) -> 0.3718876 | C26: =IF(C6=0,0,C16/C6) -> 0.44225287 | D26: =IF(D6=0,0,D16/D6) -> 0.22881515 | E26: =IF(E6=0,0,E16/E6) -> 0.32119599 | F26: =IF(F6=0,0,F16/F6) -> 0.40011118 | G26: =IF(G6=0,0,G16/G6) -> 0.36965763
A27: East | B27: =IF(B7=0,0,B17/B7) -> 0.36988293 | C27: =IF(C7=0,0,C17/C7) -> 0.42688792 | D27: =IF(D7=0,0,D17/D7) -> 0.23093597 | E27: =IF(E7=0,0,E17/E7) -> 0.31980654 | F27: =IF(F7=0,0,F17/F7) -> 0.404196 | G27: =IF(G7=0,0,G17/G7) -> 0.35875467
A28: North | B28: =IF(B8=0,0,B18/B8) -> 0.34570568 | C28: =IF(C8=0,0,C18/C8) -> 0.43822497 | D28: =IF(D8=0,0,D18/D8) -> 0.21766518 | E28: =IF(E8=0,0,E18/E8) -> 0.31781235 | F28: =IF(F8=0,0,F18/F8) -> 0.42799331 | G28: =IF(G8=0,0,G18/G8) -> 0.34030413
A29: South | B29: =IF(B9=0,0,B19/B9) -> 0.35636168 | C29: =IF(C9=0,0,C19/C9) -> 0.46990515 | D29: =IF(D9=0,0,D19/D9) -> 0.2321648 | E29: =IF(E9=0,0,E19/E9) -> 0.31823198 | F29: =IF(F9=0,0,F19/F9) -> 0.43875799 | G29: =IF(G9=0,0,G19/G9) -> 0.3401819
A30: West | B30: =IF(B10=0,0,B20/B10) -> 0.34261273 | C30: =IF(C10=0,0,C20/C10) -> 0.44992354 | D30: =IF(D10=0,0,D20/D10) -> 0.21437264 | E30: =IF(E10=0,0,E20/E10) -> 0.30780657 | F30: =IF(F10=0,0,F20/F10) -> 0.42676239 | G30: =IF(G10=0,0,G20/G10) -> 0.33994131
A31: Overall | B31: =IF(B11=0,0,B21/B11) -> 0.35959033 | C31: =IF(C11=0,0,C21/C11) -> 0.44802217 | D31: =IF(D11=0,0,D21/D11) -> 0.22371479 | E31: =IF(E11=0,0,E21/E11) -> 0.31625856 | F31: =IF(F11=0,0,F21/F11) -> 0.4135264 | G31: =IF(G11=0,0,G21/G11) -> 0.34979917
A34: Formula-based pivot (SUMIFS). To also insert a native PivotTable: Dataset ▸ Insert ▸ PivotTable ▸ Rows = Region, Columns = Product_Category, Values = Sum of Sales.

Sheet Notes_Checks
A1: Task Map, Assumptions & Error Checks
A2: Everything in this workbook is formula-driven – these checks prove the totals reconcile and that no cell returns an error
A4: Integrity Checks
A5: # | B5: Check | C5: Status
A6: 1 | B6: Pivot total sales = Dataset total sales | C6: =IF(ABS(SUM(Dataset!$E$2:$E$201)-Pivot_Summary!G11)<0.005,"OK","CHECK") -> OK
A7: 2 | B7: Pivot total profit = Dataset total profit | C7: =IF(ABS(SUM(Dataset!$I$2:$I$201)-Pivot_Summary!G21)<0.005,"OK","CHECK") -> OK
A8: 3 | B8: Monthly sales total = Dataset total sales | C8: =IF(ABS(SUM(Dataset!$E$2:$E$201)-Monthly_Growth!C19)<0.005,"OK","CHECK") -> OK
A9: 4 | B9: Customer sales total = Dataset total sales | C9: =IF(ABS(SUM(Dataset!$E$2:$E$201)-Customer_Analysis!C40)<0.005,"OK","CHECK") -> OK
A10: 5 | B10: Histogram frequencies add up to number of orders | C10: =IF(Descriptive_Stats!C31=COUNT(Dataset!$E$2:$E$201),"OK","CHECK") -> OK
A11: 6 | B11: What-if scenario at 0 pp equals baseline profit | C11: =IF(ABS(What_If!D24-What_If!B14)<0.005,"OK","CHECK") -> OK
A12: 7 | B12: Regression uses all orders | C12: =IF(Regression!B9=COUNT(Dataset!$E$2:$E$201),"OK","CHECK") -> OK
A13: 8 | B13: Dataset has no blank cells | C13: =IF(COUNTBLANK(Dataset!A2:I201)=0,"OK","CHECK") -> OK
A14: 9 | B14: Dataset has no error values | C14: =IF(SUMPRODUCT(--ISERROR(Dataset!A2:I201))=0,"OK","CHECK") -> OK
B15: Overall status | C15: =IF(COUNTIF(C6:C14,"OK")=ROWS(C6:C14),"ALL CHECKS PASSED","REVIEW CHECKS") -> ALL CHECKS PASSED
A18: Task Map (PR.2 Analyzer)
A19: # | B19: Task | C19: Sheet | D19: Technique used
A20: 1 | B20: Highlight top 10 customers by total purchase | C20: Customer_Analysis | D20: Conditional Formatting (Top 10 rule + formula rule)
A21: 2 | B21: What-If analysis: discount impact on profit | C21: What_If | D21: Input cells, scenario formulas, sensitivity table, chart
A22: 3 | B22: Linear regression: Profit vs Sales | C22: Regression | D22: ToolPak-style output using SLOPE/INTERCEPT/RSQ/FDIST/TDIST + scatter chart
A23: 4 | B23: Descriptive statistics | C23: Descriptive_Stats | D23: ToolPak-style table + histogram with COUNTIFS
A24: 5 | B24: Up / down arrows on monthly sales growth | C24: Monthly_Growth | D24: Custom number format ▲ green / ▼ red
A25: 6 | B25: Timestamp column using NOW() | C25: Dataset (col J) & Dashboard | D25: =NOW() -> 46309.485
A26: 7 | B26: High-value customers (INDEX / MATCH / filters) | C26: Customer_Analysis | D26: SUMIF group-by, RANK, INDEX+MATCH lookup, AutoFilter, drop-down lookup
A27: 8 | B27: Pivot analysis: sales by region and product | C27: Pivot_Summary | D27: SUMIFS cross-tab with heat-map formatting
A28: 9 | B28: Bar, line and pie charts for KPIs | C28: Dashboard | D28: 4 charts linked to the analysis sheets
A29: 10 | B29: Dashboard summarising insights | C29: Dashboard | D29: KPI cards + auto-generated insight sentences
A32: Data Notes & Assumptions
A33: 1. Source: the "Dataset" sheet supplied with the PR.2 project (200 orders, 9 columns, 10-Apr-2024 to 07-Apr-2025). Values were not changed.
A34: 2. Currency is not stated in the dataset, so amounts are shown without a currency symbol.
A35: 3. Data quality: the same Customer_ID appears with more than one Customer_Name (e.g. CUST014 is both "Emma Davis" and "David Thomas"). All customer analysis therefore groups by Customer_ID (30 IDs).
A36: 4. The first month (Apr-2024) starts on the 10th and the last month (Apr-2025) ends on the 7th, so both are partial months. The dashboard "best / weakest month" statement excludes the latest partial month.
A37: 5. What-if assumptions (net-of-discount sales, fixed unit cost, 3% volume uplift per +1 pp discount) are illustrative and clearly marked as inputs on the What_If sheet.
A38: 6. Colour code: blue text on yellow = input you may change; black = formula.
